maze_generator_jotbleach/__init__.py
maze_generator_jotbleach/maze.py
maze_generator_jotbleach-1.1.0.dist-info/LICENSE
maze_generator_jotbleach-1.1.0.dist-info/METADATA
maze_generator_jotbleach-1.1.0.dist-info/WHEEL
maze_generator_jotbleach-1.1.0.dist-info/top_level.txt
maze_generator_jotbleach-1.1.0.dist-info/RECORD
