Metadata-Version: 2.1
Name: maze-generator-jotbleach
Version: 1.1.0
Summary: A Python library for generating and visualizing mazes with custom properties.
Home-page: https://github.com/JotBleach/maze_generator
Author: JotBleach
Author-email: jotbleach@gmail.com
License: MIT
Classifier: Programming Language :: Python :: 3
Classifier: License :: OSI Approved :: MIT License
Classifier: Operating System :: OS Independent
Requires-Python: >=3.6
License-File: LICENSE
Requires-Dist: numpy
Requires-Dist: matplotlib
